Mongodb_JConnect/__init__.py
Mongodb_JConnect/mongo_crud.py
Mongodb_JConnect-0.0.7.dist-info/METADATA
Mongodb_JConnect-0.0.7.dist-info/WHEEL
Mongodb_JConnect-0.0.7.dist-info/top_level.txt
Mongodb_JConnect-0.0.7.dist-info/RECORD
